LICENSE.txt
MANIFEST.in
README.rst
setup.cfg
setup.py
rin/__init__.py
rin/config.py
rin/utils.py
rin_common.egg-info/PKG-INFO
rin_common.egg-info/SOURCES.txt
rin_common.egg-info/dependency_links.txt
rin_common.egg-info/requires.txt
rin_common.egg-info/top_level.txt