Metadata-Version: 1.1
Name: rin-common
Version: 0.0.5
Summary: Common library for Resrouce-In drivers
Home-page: UNKNOWN
Author: Hiroyasu OHYAMA
Author-email: oyama-hiroyasu@dmm.com
License: MIT
Platform: UNKNOWN
Classifier: License :: OSI Approved :: MIT License
Classifier: Programming Language :: Python :: 2
Classifier: Programming Language :: Python :: 2.6
Classifier: Programming Language :: Python :: 2.7
Classifier: Programming Language :: Python :: 3
Classifier: Programming Language :: Python :: 3.3
Classifier: Programming Language :: Python :: 3.4
Classifier: Programming Language :: Python :: 3.5
